{
  "project_info": {
    "project_number": "72580961193",
    "project_id": "creche-cde47",
    "storage_bucket": "creche-cde47.appspot.com"
  },


  "client": [
    {
      "client_info": {
        "mobilesdk_app_id": "1:72580961193:android:c329cddbc3570aef152ab8",
        "android_client_info": {
          "package_name": "com.huji.couchmirage"
        }
      },
      "oauth_client": [
        {
          "client_id": "72580961193-g3eespenulvfa13uocvns01lou22gr2t.apps.googleusercontent.com",
          "client_type": 3
        }
      ],
      "api_key": [
        {
          "current_key": "AIzaSyDlVvANaJl_UpcKZAmhOlE9UeXwFnOrfS8"
        }
      ],
      "services": {
        "appinvite_service": {
          "other_platform_oauth_client": [
            {
              "client_id": "72580961193-g3eespenulvfa13uocvns01lou22gr2t.apps.googleusercontent.com",
              "client_type": 3
            }
          ]
        }
      }
    }
  ],
  "configuration_version": "1"
}